MANIFEST.in
README.md
setup.cfg
setup.py
latestos/__init__.py
latestos/commands.py
latestos.egg-info/PKG-INFO
latestos.egg-info/SOURCES.txt
latestos.egg-info/dependency_links.txt
latestos.egg-info/entry_points.txt
latestos.egg-info/requires.txt
latestos.egg-info/top_level.txt
latestos/client/__init__.py
latestos/client/base.py
latestos/client/selenium/__init__.py
latestos/client/selenium/base.py
latestos/client/selenium/firefox.py
latestos/files/__init__.py
latestos/files/json.py
latestos/scraper/__init__.py
latestos/scraper/arch.py
latestos/scraper/base.py
latestos/scraper/centos.py
latestos/scraper/debian.py
latestos/scraper/fedora.py
latestos/scraper/mirrors.py
latestos/scraper/raspbian.py
latestos/scraper/ubuntu.py
latestos/scraper/utils.py
latestos/scraper/windows.py
latestos/templates/template.json
latestos/vagrantup/__init__.py
latestos/vagrantup/check.py